verysimplemoduleduo/__init__.py
verysimplemoduleduo/add.py
verysimplemoduleduo/subtract.py
verysimplemoduleduo/extras/__init__.py
verysimplemoduleduo/extras/divide.py
verysimplemoduleduo/extras/multiply.py
verysimplemoduleduo-0.0.5.dist-info/METADATA
verysimplemoduleduo-0.0.5.dist-info/WHEEL
verysimplemoduleduo-0.0.5.dist-info/top_level.txt
verysimplemoduleduo-0.0.5.dist-info/RECORD
